odoo/addons/purchase_stock_tier_validation/README.rst
odoo/addons/purchase_stock_tier_validation/__init__.py
odoo/addons/purchase_stock_tier_validation/__manifest__.py
odoo/addons/purchase_stock_tier_validation/i18n/purchase_stock_tier_validation.pot
odoo/addons/purchase_stock_tier_validation/models/__init__.py
odoo/addons/purchase_stock_tier_validation/models/stock_rule.py
odoo/addons/purchase_stock_tier_validation/readme/CONTRIBUTORS.rst
odoo/addons/purchase_stock_tier_validation/readme/DESCRIPTION.rst
odoo/addons/purchase_stock_tier_validation/static/description/icon.png
odoo/addons/purchase_stock_tier_validation/static/description/index.html
odoo/addons/purchase_stock_tier_validation/tests/__init__.py
odoo/addons/purchase_stock_tier_validation/tests/test_purchase_stock_tier_validation.py
odoo_addon_purchase_stock_tier_validation-15.0.1.0.0.3.dist-info/METADATA
odoo_addon_purchase_stock_tier_validation-15.0.1.0.0.3.dist-info/WHEEL
odoo_addon_purchase_stock_tier_validation-15.0.1.0.0.3.dist-info/top_level.txt
odoo_addon_purchase_stock_tier_validation-15.0.1.0.0.3.dist-info/RECORD
